{
  "app_id": "xrd_finder",
  "name": "XRD Phase Finder",
  "version": "1.1.1",
  "channel": "stable",
  "minimum_windows": "10.0",
  "published_at": "2026-07-08",
  "release_url": "https://github.com/ABKuznetsov/XRD_Analysis_Toolkit/releases/tag/v1.1.1",
  "release_notes_url": "https://raw.githubusercontent.com/ABKuznetsov/XRD_Analysis_Toolkit/main/XRD_Finder/RELEASE_NOTES_1.1.1.md",
  "assets": [
    {
      "name": "XRD_Phase_Finder_Setup_1.1.1.exe",
      "type": "installer",
      "platform": "windows-x64",
      "url": "https://github.com/ABKuznetsov/XRD_Analysis_Toolkit/releases/download/v1.1.1/XRD_Phase_Finder_Setup_1.1.1.exe",
      "sha256": "a01016e694e9c55ab93c9ad6e3511aa1318e4be62cc8a5e6b002ab2b3287d4ed",
      "size_bytes": 6612298
    },
    {
      "name": "XRD_Phase_Finder_macOS_1.1.1.zip",
      "type": "installer-archive",
      "platform": "macos",
      "url": "https://github.com/ABKuznetsov/XRD_Analysis_Toolkit/releases/download/v1.1.1/XRD_Phase_Finder_macOS_1.1.1.zip",
      "sha256": "3c71920ab4fcea6241edbbacf20606f91100503a28e1af68d4aa262b689dd5ed",
      "size_bytes": 4508169
    }
  ],
  "summary": [
    "Add the foundation for separate Match (%) and experimental Gain (%) candidate metrics.",
    "Keep Match (%), Gain (%) and I/Ic as separate candidate-table values for future tuning.",
    "Use the shared robust XRD background estimator inside the Finder calculation path.",
    "Build calculated Finder profiles explicitly with Cu K-alpha1/K-alpha2 doublet lines."
  ],
  "installer_url": "https://github.com/ABKuznetsov/XRD_Analysis_Toolkit/releases/download/v1.1.1/XRD_Phase_Finder_Setup_1.1.1.exe",
  "installer_sha256": "a01016e694e9c55ab93c9ad6e3511aa1318e4be62cc8a5e6b002ab2b3287d4ed"
}
